{
    "3475": "ライセンスの設定を  へんこうします",
    "10000": "1体のゴーストとレース",
    "10001": "1体のゴーストでリプレイ",
    "10002": " {arg integer|0 0}体のゴーストとレース",
    "10003": " {arg integer|0 0}体のゴーストでリプレイ",
    "10004": "HUDテキスト",
    "10005": "消去",
    "10006": "表示",
    "10007": "タイムやラップなどのテキストを  表示しません",
    "10008": "タイムやラップなどのテキストを  表示します",
    "10009": "16:9ビュー表示",
    "10010": "ふつう",
    "10011": "ひろい",
    "10012": "ワイド設定が16:9のときでも　そのままのビュー表示です",
    "10013": "ワイド設定が16:9のときでも  4:3のひろいビュー表示にします",
    "10014": "マップアイコン",
    "10015": "キャラクター",
    "10016": "Mii",
    "10017": "ミニマップの表示を  キャラクターにします",
    "10018": "ミニマップの表示を  Miiにします",
    "10019": "ゴーストのならびかえ",
    "10028": "タグの表示",
    "10029": "なし",
    "10030": "見ているゴースト",
    "10031": "すべて",
    "10032": "ゴーストのタグを  表示しません",
    "10033": "そのゴーストを見ているときのみ  タグを表示します",
    "10034": "すべてのゴーストのタグを  表示します",
    "10036": "名前",
    "10037": "タイム",
    "10038": "年月日",
    "10046": "このルールで  タイムアタックをします",
    "10057": "OFF",
    "10058": "ON",
    "10061": "コントローラ入力表示",
    "10062": "OFF",
    "10063": "ON",
    "10064": "レース中のコントローラの入力を  表示しません",
    "10065": "レース中のコントローラの入力を  表示します",
    "10066": "ゴーストのサウンド",
    "10067": "あらゆるゴーストのサウンドを  ならさないようにします",
    "10068": "そのゴーストを見ているときのみ  サウンドをならします",
    "10069": "すべてのゴーストのサウンドを  ならします",
    "10073": "タイムアタックなどを  １人であそびます",
    "10074": "設定を変更したり  Miiをかえることができます",
    "10082": "MKW-SPの設定",
    "10083": "Service Pack",
    "10087": "アップデート",
    "10088": "チャンネル",
    "10089": "MKW-SPについて",
    "10091": "「MKW-SPチャンネル」を\nインストールしますか？",
    "10092": "MKW-SPのアップデートが利用できます。\nインストールをしますか？",
    "10093": "「MKW-SPチャンネル」は\nすでにインストールされています",
    "10094": "「MKW-SPチャンネル」の最新のバージョンは\nすでにインストールされています",
    "10095": "「MKW-SPチャンネル」を\nインストールしています",
    "10096": "「MKW-SPチャンネル」を\nアップデートしています",
    "10097": "「MKW-SPチャンネル」が\nインストールされました！",
    "10098": "「MKW-SPチャンネル」の\nインストールに失敗しました。",
    "10099": "「MKW-SPチャンネル」が\nアップデートされました！",
    "10100": "「MKW-SPチャンネル」の\nアップデートに失敗しました。",
    "10101": "「MKW-SPチャンネル」は\nリリースビルドからのみインストールできます",
    "10102": "アップデートを確認しています\n{arg message|0}",
    "10103": "最新バージョンのMKW-SPが利用できます！\n{arg string|0} → {arg string|1}",
    "10104": "MKW-SPの最新のバージョン({arg string|0})は\nすでにインストールされています。",
    "10105": "MKW-SPのアップデートの確認に失敗しました。",
    "10107": "MKW-SPをアップデートしています\n{arg message|0}",
    "10108": "MKW-SPはバージョン{arg string|0}から{arg string|1}にアップデートされました！\n更新をゆうこうにするには  もういちど起動しなおしてください。",
    "10109": "MKW-SPの\nアップデートに失敗しました。",
    "10110": "MKW-SPを起動しなおしますか？",
    "10111": "MKW-SPは  リリースビルドからのみ\nアップデートすることができます",
    "10112": "サーバーに接続しています",
    "10113": "バージョン情報を送信しています",
    "10114": "バージョン情報を受信しています",
    "10115": "コンテンツをダウンロードしています\n{arg string|0} MiB of {arg string|1} MiB - {arg string|2} MiB/s",
    "10116": "コンテンツを移動しています",
    "10118": "レース",
    "10119": "タイムアタック",
    "10120": "ライセンス",
    "10121": "順位",
    "10122": "グランプリとVS",
    "10123": "つねに",
    "10124": "グランプリとVSのみ  順位を表示します",
    "10125": "つねに画面に  順位を表示します",
    "10126": "サウンド",
    "10127": "アイテムのBGM",
    "10128": "なし",
    "10129": "サンダー/つぶれた時のみ",
    "10130": "すべて",
    "10134": "ファイナルラップサウンド",
    "10135": "プレイ中のみ",
    "10136": "つねに",
    "10137": "プレイ時のみ  ファイナルラップのサウンドをならします",
    "10138": "リプレイ中でも  ファイナルラップのサウンドをならします",
    "10139": "ファイナルラップテンポ上げ",
    "10140": "なし",
    "10141": "ストイック",
    "10142": "ダイナミック",
    "10143": "ファイナルラップに  「_N」のBRSTMを使用します",
    "10144": "ファイナルラップに  「_F」のBRSTMを使用します",
    "10145": "「_N」のBRSTMから  ファイナルラップのBGMを生成します",
    "10151": "初期化しています",
    "10154": "SDカード",
    "10155": "SDカード",
    "10156": "USB",
    "10157": "USB",
    "10158": "ネットワーク",
    "10159": "ネットワーク",
    "10160": "ミッションラン",
    "10161": "いろいろなミッションを  あそびます",
    "10164": "ゴースト",
    "10165": "ゴースト",
    "10167": "OFF",
    "10168": "ON",
    "10171": "タイム",
    "10172": "日付",
    "10173": "最速ラップ",
    "10176": "ゴーストを終了タイム順に  ならべかえます",
    "10177": "ゴーストを作成された日付順に  ならべかえます",
    "10178": "ゴーストを最速タイム順に  ならべかえます",
}