{
    "version": 10,
    "sections": [
        {
            "magic": "pat1",
            "id": 14,
            "groups": [],
            "name": "active_off_to_on",
            "start frame": 100,
            "end frame": 103,
            "descending bind": true,
        },
        {
            "magic": "pai1",
            "frame count": 4,
            "loop": false,
            "tpls": [],
            "contents": [
                {
                    "name": "active_base",
                    "kind": "pane",
                    "animations": [
                        {
                            "magic": "RLVC",
                            "targets": [
                                {
                                    "id": 0,
                                    "kind": "pane alpha",
                                    "curve type": "hermite",
                                    "keys": [
                                        {
                                            "frame": 0.0,
                                            "value": 0.0,
                                            "slope": 85.0,
                                        },
                                        {
                                            "frame": 3.0,
                                            "value": 255.0,
                                            "slope": 85.0,
                                        },
                                    ],
                                },
                            ],
                        },
                    ],
                },
                {
                    "name": "active_mii",
                    "kind": "pane",
                    "animations": [
                        {
                            "magic": "RLVC",
                            "targets": [
                                {
                                    "id": 0,
                                    "kind": "pane alpha",
                                    "curve type": "hermite",
                                    "keys": [
                                        {
                                            "frame": 0.0,
                                            "value": 0.0,
                                            "slope": 85.0,
                                        },
                                        {
                                            "frame": 3.0,
                                            "value": 255.0,
                                            "slope": 85.0,
                                        },
                                    ],
                                },
                            ],
                        },
                    ],
                },
                {
                    "name": "active_name",
                    "kind": "pane",
                    "animations": [
                        {
                            "magic": "RLVC",
                            "targets": [
                                {
                                    "id": 0,
                                    "kind": "pane alpha",
                                    "curve type": "hermite",
                                    "keys": [
                                        {
                                            "frame": 0.0,
                                            "value": 0.0,
                                            "slope": 85.0,
                                        },
                                        {
                                            "frame": 3.0,
                                            "value": 255.0,
                                            "slope": 85.0,
                                        },
                                    ],
                                },
                            ],
                        },
                    ],
                },
                {
                    "name": "active_flag",
                    "kind": "pane",
                    "animations": [
                        {
                            "magic": "RLVC",
                            "targets": [
                                {
                                    "id": 0,
                                    "kind": "pane alpha",
                                    "curve type": "hermite",
                                    "keys": [
                                        {
                                            "frame": 0.0,
                                            "value": 0.0,
                                            "slope": 85.0,
                                        },
                                        {
                                            "frame": 3.0,
                                            "value": 255.0,
                                            "slope": 85.0,
                                        },
                                    ],
                                },
                            ],
                        },
                    ],
                },
                {
                    "name": "active_chara",
                    "kind": "pane",
                    "animations": [
                        {
                            "magic": "RLVC",
                            "targets": [
                                {
                                    "id": 0,
                                    "kind": "pane alpha",
                                    "curve type": "hermite",
                                    "keys": [
                                        {
                                            "frame": 0.0,
                                            "value": 0.0,
                                            "slope": 85.0,
                                        },
                                        {
                                            "frame": 3.0,
                                            "value": 255.0,
                                            "slope": 85.0,
                                        },
                                    ],
                                },
                            ],
                        },
                    ],
                },
                {
                    "name": "active_machine",
                    "kind": "pane",
                    "animations": [
                        {
                            "magic": "RLVC",
                            "targets": [
                                {
                                    "id": 0,
                                    "kind": "pane alpha",
                                    "curve type": "hermite",
                                    "keys": [
                                        {
                                            "frame": 0.0,
                                            "value": 0.0,
                                            "slope": 85.0,
                                        },
                                        {
                                            "frame": 3.0,
                                            "value": 255.0,
                                            "slope": 85.0,
                                        },
                                    ],
                                },
                            ],
                        },
                    ],
                },
                {
                    "name": "active_time",
                    "kind": "pane",
                    "animations": [
                        {
                            "magic": "RLVC",
                            "targets": [
                                {
                                    "id": 0,
                                    "kind": "pane alpha",
                                    "curve type": "hermite",
                                    "keys": [
                                        {
                                            "frame": 0.0,
                                            "value": 0.0,
                                            "slope": 85.0,
                                        },
                                        {
                                            "frame": 3.0,
                                            "value": 255.0,
                                            "slope": 85.0,
                                        },
                                    ],
                                },
                            ],
                        },
                    ],
                },
            ],
        },
    ],
}
